{"@context":["https://www.w3.org/ns/did/v1","https://w3id.org/security/suites/jws-2020/v1"],"id":"did:web:jlmalone.github.io","verificationMethod":[{"id":"did:web:jlmalone.github.io#wc-notify-subscribe-key","type":"JsonWebKey2020","controller":"did:web:jlmalone.github.io","publicKeyJwk":{"kty":"OKP","crv":"X25519","x":"avM2x2it2odbZ9T3s6y3zOoBJWBGftTr5cUNRqbGvlI"}},{"id":"did:web:jlmalone.github.io#wc-notify-authentication-key","type":"JsonWebKey2020","controller":"did:web:jlmalone.github.io","publicKeyJwk":{"kty":"OKP","crv":"Ed25519","x":"Jwy2p9XOEgrjXp403IkQmO6exMyIq3QFXFjHCfaXJTE"}}],"keyAgreement":["did:web:jlmalone.github.io#wc-notify-subscribe-key"],"authentication":["did:web:jlmalone.github.io#wc-notify-authentication-key"]}
